Metadata-Version: 2.4
Name: logomaker
Version: 0.8.6
Summary: Package for making Sequence Logos
Project-URL: Documentation, http://logomaker.readthedocs.io
Project-URL: Repository, https://github.com/jbkinney/logomaker
Author-email: "Ammar Tareen and Justin B. Kinney" <tareen@cshl.edu>
License: MIT License
License-File: LICENSE
Classifier: Development Status :: 3 - Alpha
Classifier: License :: OSI Approved :: MIT License
Classifier: Programming Language :: Python :: 3.12
Classifier: Topic :: Scientific/Engineering :: Bio-Informatics
Requires-Python: >=3.8
Requires-Dist: matplotlib
Requires-Dist: numpy
Requires-Dist: pandas
